entry_on_kitchen/Kitchen.py
entry_on_kitchen/__init__.py
entry_on_kitchen-0.3.2.dist-info/METADATA
entry_on_kitchen-0.3.2.dist-info/WHEEL
entry_on_kitchen-0.3.2.dist-info/top_level.txt
entry_on_kitchen-0.3.2.dist-info/RECORD
