Metadata-Version: 2.4
Name: entry-on-kitchen
Version: 0.3.2
Summary: Official Python Module for using entry blocks on kitchen
Author: Endevre Technologies
Author-email: Endevre Technologies <contact@endevre.com>
License: Proprietary
Project-URL: Homepage, https://github.com/endevre/entry-on-kitchen-python
Project-URL: Documentation, https://github.com/endevre/entry-on-kitchen-python#readme
Project-URL: Repository, https://github.com/endevre/entry-on-kitchen-python
Project-URL: Bug Tracker, https://github.com/endevre/entry-on-kitchen-python/issues
Keywords: kitchen,entry,api,pipeline,streaming
Classifier: Development Status :: 5 - Production/Stable
Classifier: Intended Audience :: Developers
Classifier: Topic :: Software Development :: Libraries :: Python Modules
Classifier: Programming Language :: Python :: 3
Classifier: Programming Language :: Python :: 3.7
Classifier: Programming Language :: Python :: 3.8
Classifier: Programming Language :: Python :: 3.9
Classifier: Programming Language :: Python :: 3.10
Classifier: Programming Language :: Python :: 3.11
Classifier: Programming Language :: Python :: 3.12
Requires-Python: >=3.7
Requires-Dist: requests>=2.25.0
Provides-Extra: dev
Requires-Dist: pytest<9,>=8; extra == "dev"
Requires-Dist: build>=1.0.0; extra == "dev"
Requires-Dist: twine>=4.0.0; extra == "dev"
Dynamic: author
Dynamic: requires-python
